rebase_migrations-0.5.0.dist-info/METADATA
rebase_migrations-0.5.0.dist-info/WHEEL
rebase_migrations-0.5.0.dist-info/licenses/LICENSE
rebase_migrations/__init__.py
rebase_migrations/rebase_migrations.abi3.so
rebase_migrations-0.5.0.dist-info/RECORD
