Metadata-Version: 2.4
Name: rebase-migrations
Version: 0.5.0
Classifier: Development Status :: 4 - Beta
Classifier: Intended Audience :: Developers
Classifier: License :: OSI Approved :: MIT License
Classifier: Programming Language :: Python :: 3
Classifier: Programming Language :: Python :: 3.8
Classifier: Programming Language :: Python :: 3.9
Classifier: Programming Language :: Python :: 3.10
Classifier: Programming Language :: Python :: 3.11
Classifier: Programming Language :: Python :: 3.12
Classifier: Programming Language :: Rust
Classifier: Topic :: Software Development :: Version Control :: Git
Classifier: Topic :: Database
Classifier: Framework :: Django
License-File: LICENSE
Summary: Python library for Django migration conflict resolution during git rebases
Keywords: django,migrations,git,rebase,conflict-resolution
Home-Page: https://github.com/reinhash/rebase-migrations
Author-email: Reinhard Scheuerle <reinhard.scheuerle@gmail.com>
License-Expression: MIT
Requires-Python: >=3.8
Project-URL: Homepage, https://github.com/reinhash/rebase-migrations
Project-URL: Repository, https://github.com/reinhash/rebase-migrations
